dbt_metamodels/__init__.py
dbt_metamodels-0.1.0.data/purelib/zzz_dbt_metamodels.pth
dbt_metamodels-0.1.0.dist-info/WHEEL
dbt_metamodels-0.1.0.dist-info/METADATA
dbt_metamodels-0.1.0.dist-info/RECORD
