Metadata-Version: 2.4
Name: dbt-metamodels
Version: 0.1.0
Summary: Define your dbt models in yaml
Keywords: dbt,models,yaml
Author: Boris Klyus
Author-email: Boris Klyus <klyusba@gmail.com>
License-Expression: MIT
Requires-Dist: dbt-core>=1.5.0
Maintainer: Boris Klyus
Maintainer-email: Boris Klyus <klyusba@gmail.com>
Requires-Python: >=3.8
Project-URL: Homepage, https://github.com/klyusba/dbt-metamodels
Project-URL: Documentation, https://github.com/klyusba/dbt-metamodels
Project-URL: Repository, https://github.com/klyusba/dbt-metamodels.git
Project-URL: Issues, https://github.com/klyusba/dbt-metamodels/issues
